README.md
setup.cfg
setup.py
xbim_flex/__init__.py
xbim_flex.egg-info/PKG-INFO
xbim_flex.egg-info/SOURCES.txt
xbim_flex.egg-info/dependency_links.txt
xbim_flex.egg-info/requires.txt
xbim_flex.egg-info/top_level.txt
xbim_flex/aim/__init__.py
xbim_flex/aim/api_client.py
xbim_flex/aim/configuration.py
xbim_flex/aim/exceptions.py
xbim_flex/aim/model_utils.py
xbim_flex/aim/rest.py
xbim_flex/aim/api/__init__.py
xbim_flex/aim/api/admin_api.py
xbim_flex/aim/api/applications_api.py
xbim_flex/aim/api/assemblies_api.py
xbim_flex/aim/api/assets_api.py
xbim_flex/aim/api/attributes_api.py
xbim_flex/aim/api/component_types_api.py
xbim_flex/aim/api/components_api.py
xbim_flex/aim/api/contacts_api.py
xbim_flex/aim/api/diagnostics_api.py
xbim_flex/aim/api/document_files_api.py
xbim_flex/aim/api/documents_api.py
xbim_flex/aim/api/entities_api.py
xbim_flex/aim/api/facilities_api.py
xbim_flex/aim/api/floorplans_api.py
xbim_flex/aim/api/issues_api.py
xbim_flex/aim/api/jobs_api.py
xbim_flex/aim/api/levels_api.py
xbim_flex/aim/api/logs_api.py
xbim_flex/aim/api/model_files_api.py
xbim_flex/aim/api/model_mapping_api.py
xbim_flex/aim/api/models_api.py
xbim_flex/aim/api/resources_api.py
xbim_flex/aim/api/schedules_api.py
xbim_flex/aim/api/sites_api.py
xbim_flex/aim/api/spaces_api.py
xbim_flex/aim/api/spares_api.py
xbim_flex/aim/api/stats_api.py
xbim_flex/aim/api/systems_api.py
xbim_flex/aim/api/thumbnails_api.py
xbim_flex/aim/api/wexbim_api.py
xbim_flex/aim/api/zones_api.py
xbim_flex/aim/apis/__init__.py
xbim_flex/aim/model/__init__.py
xbim_flex/aim/model/application.py
xbim_flex/aim/model/assembly_diagnostics.py
xbim_flex/aim/model/assembly_info.py
xbim_flex/aim/model/assembly_item.py
xbim_flex/aim/model/asset.py
xbim_flex/aim/model/asset_create.py
xbim_flex/aim/model/asset_edit.py
xbim_flex/aim/model/asset_segment.py
xbim_flex/aim/model/assets_assign_by_tenantid_and_assetid_request.py
xbim_flex/aim/model/attribute_definition.py
xbim_flex/aim/model/attribute_definition_create.py
xbim_flex/aim/model/attribute_definition_edit.py
xbim_flex/aim/model/attribute_definition_entity.py
xbim_flex/aim/model/attribute_value.py
